[
    {
        "wav": "0.wav",
        "text": "Whoa!"
    },
    {
        "wav": "1.wav",
        "text": "Nooooooooooooooooooooooooooooooooo nooooooo"
    },
    {
        "wav": "2.wav",
        "text": "Origin point of long-range lasers confirmed."
    },
    {
        "wav": "3.wav",
        "text": "11B, down."
    },
    {
        "wav": "4.wav",
        "text": "Our HO-229 cancellers are ineffective."
    },
    {
        "wav": "5.wav",
        "text": "7e down."
    },
    {
        "wav": "6.wav",
        "text": "Everything that lives is designed to end."
    },
    {
        "wav": "7.wav",
        "text": "We are perpetually trapped."
    },
    {
        "wav": "8.wav",
        "text": "in a never-ending spiral of life and death."
    },
    {
        "wav": "9.wav",
        "text": "Is this a curse?"
    },
    {
        "wav": "10.wav",
        "text": "or some kind of punishment?"
    },
    {
        "wav": "11.wav",
        "text": "I often think about the god who blessed us with this cryptic puzzle."
    },
    {
        "wav": "12.wav",
        "text": "and wonder if we'll ever have the chance to kill him."
    },
    {
        "wav": "13.wav",
        "text": "2B here. All units have penetrated the stratosphere."
    },
    {
        "wav": "14.wav",
        "text": "Autopilot systems green across the board."
    },
    {
        "wav": "15.wav",
        "text": "We've passed the 50-kilometer threshold and are proceeding toward the target."
    },
    {
        "wav": "16.wav",
        "text": "Understood."
    },
    {
        "wav": "17.wav",
        "text": "12H down."
    },
    {
        "wav": "18.wav",
        "text": "All units activate manual mode and rely on visuals to evade."
    },
    {
        "wav": "19.wav",
        "text": "Requesting permission to engage."
    },
    {
        "wav": "20.wav",
        "text": "1D down. Assuming Captain's duties."
    },
    {
        "wav": "21.wav",
        "text": "Multiple surrounding enemy air units confirmed. Requesting permission to assume mobile configuration."
    },
    {
        "wav": "22.wav",
        "text": "4B down."
    },
    {
        "wav": "23.wav",
        "text": "2B to operator 6-0."
    },
    {
        "wav": "24.wav",
        "text": "All allied units down."
    },
    {
        "wav": "25.wav",
        "text": "The operation is compromised, awaiting further orders."
    },
    {
        "wav": "26.wav",
        "text": "Understood."
    },
    {
        "wav": "27.wav",
        "text": "んっ"
    },
    {
        "wav": "28.wav",
        "text": "9S"
    },
    {
        "wav": "29.wav",
        "text": "Thank you."
    },
    {
        "wav": "30.wav",
        "text": "for uploading my data to the bunker."
    },
    {
        "wav": "31.wav",
        "text": "I see."
    },
    {
        "wav": "32.wav",
        "text": "I'm fine 9S. There's something about your voice that calms me."
    },
    {
        "wav": "33.wav",
        "text": "Captain, I think..."
    },
    {
        "wav": "34.wav",
        "text": "So... mission complete and all that, huh?"
    },
    {
        "wav": "35.wav",
        "text": "The Goliaths were wiped out and we secured a route into enemy territory. Now we can-"
    },
    {
        "wav": "36.wav",
        "text": "Yeah?"
    },
    {
        "wav": "37.wav",
        "text": "[Silent]"
    },
    {
        "wav": "38.wav",
        "text": "Um, I did that? Sorry, I don't remember."
    },
    {
        "wav": "39.wav",
        "text": "There wasn't a whole lot of bandwidth down there, you know?"
    },
    {
        "wav": "40.wav",
        "text": "I probably only had enough time to back up your memories."
    },
    {
        "wav": "41.wav",
        "text": "Mine are only intact up to the point just before we rendezvoused."
    },
    {
        "wav": "42.wav",
        "text": "Initializing Systems"
    },
    {
        "wav": "43.wav",
        "text": "2B, can you hear me? I'm starting your boot sequence."
    },
    {
        "wav": "44.wav",
        "text": "Pull up the settings screen."
    },
    {
        "wav": "45.wav",
        "text": "First you'll want to check your brightness settings."
    },
    {
        "wav": "46.wav",
        "text": "Hmm? You don't know how to adjust the brightness? I think it's set up to respond to some kind of input."
    },
    {
        "wav": "47.wav",
        "text": "Eh, alright. Just give me a second here."
    },
    {
        "wav": "48.wav",
        "text": "Okay, I found the guide. If you can just follow that, it'll make things easier."
    },
    {
        "wav": "49.wav",
        "text": "Right then, let's get started."
    },
    {
        "wav": "50.wav",
        "text": "We'll go through each adjustment in order."
    },
    {
        "wav": "51.wav",
        "text": "Okay, how does this look?"
    },
    {
        "wav": "52.wav",
        "text": "Roger that."
    },
    {
        "wav": "53.wav",
        "text": "Oh, and I should probably let you know that this entire process is being recorded for posterity."
    },
    {
        "wav": "54.wav",
        "text": "Now let's take a look at your voice recognition settings."
    },
    {
        "wav": "55.wav",
        "text": "Seems your voice recognition is set to mute, which isn't gonna work. I'm gonna call out to you now. Make sure you can hear my voice."
    },
    {
        "wav": "56.wav",
        "text": "Ma'am? Are you there? Can you hear me?"
    },
    {
        "wav": "57.wav",
        "text": "Uh, hello? Go ahead and adjust your settings so you can hear me, alright?"
    },
    {
        "wav": "58.wav",
        "text": "Adjust the settings until you can hear my voice."
    },
    {
        "wav": "59.wav",
        "text": "Uh, could you try and pick up the pace a little bit? This is getting embarrassing."
    },
    {
        "wav": "60.wav",
        "text": "Wait, you shouldn't be able to hear me now."
    },
    {
        "wav": "61.wav",
        "text": "Alright, are we good now?"
    },
    {
        "wav": "62.wav",
        "text": "Okay, settings should all be good to go."
    },
    {
        "wav": "63.wav",
        "text": "Oh, uh... Thank you. Anyway, that takes care of the settings."
    },
    {
        "wav": "64.wav",
        "text": "What the heck? My pulse rate is rising."
    },
    {
        "wav": "65.wav",
        "text": "Hmm. It seems to be back to normal now. How odd."
    },
    {
        "wav": "66.wav",
        "text": "Hold on. Your self-destruct permissions are missing. Wait a sec, we need to restore those."
    },
    {
        "wav": "67.wav",
        "text": "I could set it for you, but you should probably do it yourself. Regulations and all, you know?"
    },
    {
        "wav": "68.wav",
        "text": "Huh? Wait, no, you need to leave that turned on."
    },
    {
        "wav": "69.wav",
        "text": "Yeah, you can't really do that. It needs to be turned on except in very specific cases."
    },
    {
        "wav": "70.wav",
        "text": "I'm afraid I can't leave this as is, ma'am. Please give your permission."
    },
    {
        "wav": "71.wav",
        "text": "Hey, come on now. I'm just trying to follow regulations here."
    },
    {
        "wav": "72.wav",
        "text": "Okay, good. If things go wrong during an OP, you may have to sacrifice yourself in order to finish it, so..."
    },
    {
        "wav": "73.wav",
        "text": "Once you're finished making adjustments, you can go ahead and close this out."
    },
    {
        "wav": "74.wav",
        "text": "Oh, I see you've turned vibration detection on. Let's run a check to make sure it's working."
    },
    {
        "wav": "75.wav",
        "text": "I'm gonna tap you on the shoulders, alright?"
    },
    {
        "wav": "76.wav",
        "text": "How was that? Did you feel it?"
    },
    {
        "wav": "77.wav",
        "text": "Okay, check complete."
    },
    {
        "wav": "78.wav",
        "text": "Huh? That's odd. Everything should be set up correctly."
    },
    {
        "wav": "79.wav",
        "text": "Here, let me try somewhere else. I'm gonna tap you on the arm this time, okay?"
    },
    {
        "wav": "80.wav",
        "text": "Did you feel that?"
    },
    {
        "wav": "81.wav",
        "text": "Okay, check complete."
    },
    {
        "wav": "82.wav",
        "text": "Huh? Really?"
    },
    {
        "wav": "83.wav",
        "text": "Tooby must have felt that. Maybe she's just messing with me."
    },
    {
        "wav": "84.wav",
        "text": "Well, if you say so... How about this?"
    },
    {
        "wav": "85.wav",
        "text": "Should I tap her here though? She might get angry at me."
    },
    {
        "wav": "86.wav",
        "text": "Uh, how was that?"
    },
    {
        "wav": "87.wav",
        "text": "Okay, check complete."
    },
    {
        "wav": "88.wav",
        "text": "Are you serious?"
    },
    {
        "wav": "89.wav",
        "text": "You didn't feel anything just now?"
    },
    {
        "wav": "90.wav",
        "text": "Well then, let's try something else."
    },
    {
        "wav": "91.wav",
        "text": "No turning back now, I guess."
    },
    {
        "wav": "92.wav",
        "text": "Well..."
    },
    {
        "wav": "93.wav",
        "text": "Okay, great. Thanks."
    },
    {
        "wav": "94.wav",
        "text": "Hmm. I don't know what's causing this, so we'll need to run some precision diagnostics later."
    },
    {
        "wav": "95.wav",
        "text": "Regardless, that's the end of the check for now."
    },
    {
        "wav": "96.wav",
        "text": "I know no one likes the idea of self-destructing."
    },
    {
        "wav": "97.wav",
        "text": "but that's what regulations call for. Still, I'll keep it a secret from the commander."
    },
    {
        "wav": "98.wav",
        "text": "You don't want to hear my voice? I mean, it's your choice and all, but..."
    },
    {
        "wav": "99.wav",
        "text": "You undid the settings I walked you through."
    },
    {
        "wav": "100.wav",
        "text": "Uh... this isn't about me, is it? Because I'm really hoping we'll be a good team going forward."
    },
    {
        "wav": "101.wav",
        "text": "Heh. Ma'am, you fiddled with so many things, I ended up hitting my Mac's storage limit. I'll have to stop recording for now."
    },
    {
        "wav": "102.wav",
        "text": "This is command. Yorha squadron, come in."
    },
    {
        "wav": "103.wav",
        "text": "This is Operator 6O. All units confirmed."
    },
    {
        "wav": "104.wav",
        "text": "Understood. Once you reach their anti-air defenses, proceed to manual-attack formation..."
    },
    {
        "wav": "105.wav",
        "text": "then destroy the Goliath class unit by any means necessary and gather what data you can."
    },
    {
        "wav": "106.wav",
        "text": "Permission granted."
    },
    {
        "wav": "107.wav",
        "text": "Permission granted."
    },
    {
        "wav": "108.wav",
        "text": "Uh, Operator to 2B."
    },
    {
        "wav": "109.wav",
        "text": "We need you to rendezvous with Unit 9S and begin gathering data on the local terrain."
    },
    {
        "wav": "110.wav",
        "text": "Already engaged. Free movement unlocked."
    },
    {
        "wav": "111.wav",
        "text": "Alert: Enemy units sighted ahead."
    }
]