[
    {
        "id": "M1030_S0400_G0250_001_a2b",
        "jp": "あれは……？",
        "en": "What's that?",
        "ru": "Что это такое?"
    },
    {
        "id": "M1030_S0400_G0260_001_a9s",
        "jp": "ああ、２Ｂは見たことなかったんですね。",
        "en": "Oh, right. You wouldn't have seen that before.",
        "ru": "О, верно. Ты же никогда не видела этого прежде."
    },
    {
        "id": "M1030_S0400_G0270_001_a9s",
        "jp": "あれは地上からバンカーや月面の人類基地に向けて\\n資材を打ち上げているんです。",
        "en": "They're sending supplies up from Earth to the moon and the Bunker.",
        "ru": "Они отправляют материалы с Земли на Луну и в Бункер."
    },
    {
        "id": "M1030_S0400_G0280_001_a9s",
        "jp": "宇宙空間では資材も燃料もありませんから。",
        "en": "There are no spare parts or fuel in space, after all.",
        "ru": "Ведь в космосе нет ни запчастей, ни топлива."
    },
    {
        "id": "M1030_S0400_G0290_001_a2b",
        "jp": "なるほど。",
        "en": "Huh.",
        "ru": "Вот как."
    },
    {
        "id": "M1030_S0400_G0300_001_a2b",
        "jp": "……どうして機械生命体や、それを作った宇宙人は\\nバンカーを直接攻撃しないんだろう。",
        "en": "So why don't the machines—or the aliens who created them—attack the Bunker directly?",
        "ru": "Так почему машины, или же пришельцы, которые создали их, не напали непосредственно на Бункер?"
    },
    {
        "id": "M1030_S0400_G0310_001_a2b",
        "jp": "元々、宇宙から来てる筈なのに……",
        "en": "They originally came here from outer space, right?",
        "ru": "Они изначально прибыли из космоса, так ведь?"
    },
    {
        "id": "M1030_S0400_G0320_001_a9s",
        "jp": "その原因については色んな議論がされているんですけど、",
        "en": "Well, there are a few theories about that...",
        "ru": "Существует несколько теорий..."
    },
    {
        "id": "M1030_S0400_G0330_001_a9s",
        "jp": "結論は出てないんですよね。",
        "en": "But no one knows for sure.",
        "ru": "Но никто не может сказать наверняка."
    },
    {
        "id": "M1030_S0400_G0340_001_a9s",
        "jp": "宇宙人の考える事は、よく判らないです。",
        "en": "Hard to tell what an alien is thinking, you know?",
        "ru": "Трудно же сказать о чём думают инопланетяне, как думаешь?"
    }
]